<?xml version="1.0" encoding="UTF-8"?>
<Entities
 build="b103"
 majorVersion="8"
 minorVersion="5"
 modelPersistenceProviderPackage="PostgresPersistenceProviderPackage"
 revision="5"
 schemaVersion="1054"
 universal="password">
    <StyleDefinitions>
        <StyleDefinition
         aspect.isThemeObject="true"
         description="Default gauge border style"
         documentationContent=""
         homeMashup=""
         lastModifiedDate="2020-07-15T16:10:22.667Z"
         name="PTC.SimulatorDefaultGaugeBorder.Style"
         projectName="Simulator"
         tags="">
            <avatar></avatar>
            <DesignTimePermissions>
                <Create></Create>
                <Read></Read>
                <Update></Update>
                <Delete></Delete>
                <Metadata></Metadata>
            </DesignTimePermissions>
            <RunTimePermissions></RunTimePermissions>
            <VisibilityPermissions>
                <Visibility></Visibility>
            </VisibilityPermissions>
            <ConfigurationTableDefinitions></ConfigurationTableDefinitions>
            <ConfigurationTables></ConfigurationTables>
            <content>
            <![CDATA[
            {
              "backgroundColor" : "rgba(204,204,204,1)",
              "displayString" : "",
              "fontEmphasisBold" : false,
              "fontEmphasisItalic" : false,
              "fontEmphasisUnderline" : false,
              "foregroundColor" : "",
              "lineColor" : "#b3b3b3",
              "lineStyle" : "solid",
              "lineThickness" : 1,
              "secondaryBackgroundColor" : "rgba(204,204,204,1)",
              "textSize" : "normal"
            }
            ]]>
            </content>
        </StyleDefinition>
    </StyleDefinitions>
</Entities>
